phi/__init__.py
phi/export.py
phi/preprocess.py
phi/train.py
phi/tt.py
phi/assets/ddsp_config.yaml
phi/assets/data/chirp/chirp.wav
phi/assets/data/test_assets/conditional_parameters.npy
phi/assets/data/test_assets/loudness.npy
phi/assets/data/test_assets/pitchs.npy
phi/assets/data/test_assets/signals.npy
phi/ddsp/__init__.py
phi/ddsp/conditions.py
phi/ddsp/core.py
phi/ddsp/model.py
phi/ddsp/utils.py
phi_ddsp-1.0.46.dist-info/LICENSE
phi_ddsp-1.0.46.dist-info/WHEEL
phi_ddsp-1.0.46.dist-info/METADATA
phi_ddsp-1.0.46.dist-info/RECORD
