Metadata-Version: 2.1
Name: phi-ddsp
Version: 1.0.46
Summary: phi
Author-email: Max Ardito <maxwellardito@gmail.com>
Requires-Python: >=3.10
Classifier: License :: OSI Approved :: MIT License
Requires-Dist: numpy>=1.19.4
Requires-Dist: crepe>=0.0.11
Requires-Dist: librosa>=0.8.0
Requires-Dist: einops>=0.3.0
Requires-Dist: tqdm>=4.46.0
Requires-Dist: torch>=1.7.0
Requires-Dist: effortless_config>=0.7.0
Requires-Dist: SoundFile>=0.10.3.post1
Requires-Dist: Flask>=1.1.2
Requires-Dist: PyYAML>=5.3.1
Requires-Dist: tensorboard
Requires-Dist: tensorflow
Requires-Dist: pytest
Requires-Dist: datasets
Project-URL: home-page, https://github.com/maxardito/phi
